{
  "active": false,
  "connections": {
    "When clicking \"Execute Workflow\"": {
      "main": [
        [
          {
            "node": "Postgres",
            "type": "main",
            "index": 0
          }
        ]
      ]
    },
    "Postgres": {
      "main": [
        [
          {
            "node": "Postgres1",
            "type": "main",
            "index": 0
          }
        ]
      ]
    }
  },
  "createdAt": "2025-02-04T12:14:45.803Z",
  "id": "njXO7IDXpPqBPdjK",
  "meta": null,
  "name": "My workflow 28",
  "nodes": [
    {
      "parameters": {},
      "id": "998a1c54-3a6d-4b47-8200-54dd75d785d5",
      "name": "When clicking \"Execute Workflow\"",
      "type": "n8n-nodes-base.manualTrigger",
      "typeVersion": 1,
      "position": [
        880,
        520
      ]
    },
    {
      "parameters": {
        "operation": "select",
        "schema": {
          "__rl": true,
          "mode": "list",
          "value": "public"
        },
        "table": {
          "__rl": true,
          "value": "net_enquiry",
          "mode": "name"
        },
        "returnAll": true,
        "where": {
          "values": [
            {
              "column": "coming_from",
              "value": "superbot_camp_1374"
            }
          ]
        },
        "options": {}
      },
      "id": "2683cac4-fe27-4b26-8fc7-ed95e5c141a2",
      "name": "Postgres",
      "type": "n8n-nodes-base.postgres",
      "typeVersion": 2.2,
      "position": [
        1280,
        520
      ],
      "credentials": {
        "postgres": {
          "id": "VPJUosohtvWNBW4H",
          "name": "MF Prod (DO NOT USE)"
        }
      }
    },
    {
      "parameters": {
        "operation": "update",
        "schema": {
          "__rl": true,
          "mode": "list",
          "value": "public"
        },
        "table": {
          "__rl": true,
          "value": "net_enquiry",
          "mode": "name"
        },
        "columns": {
          "mappingMode": "defineBelow",
          "value": {
            "status": false,
            "whatsapp_opt_in": false,
            "register_for_webinar": false,
            "intrested_to_work_in_us": false,
            "isFromWelcomeBack": false,
            "id": "={{ $json.id }}",
            "campaign_id": 1366
          },
          "matchingColumns": [
            "id"
          ],
          "schema": [
            {
              "id": "id",
              "displayName": "id",
              "required": false,
              "defaultMatch": true,
              "display": true,
              "type": "number",
              "canBeUsedToMatch": true,
              "removed": false
            },
            {
              "id": "status",
              "displayName": "status",
              "required": true,
              "defaultMatch": false,
              "display": true,
              "type": "boolean",
              "canBeUsedToMatch": true
            },
            {
              "id": "created_by",
              "displayName": "created_by",
              "required": false,
              "defaultMatch": false,
              "display": true,
              "type": "number",
              "canBeUsedToMatch": true
            },
            {
              "id": "updated_by",
              "displayName": "updated_by",
              "required": false,
              "defaultMatch": false,
              "display": true,
              "type": "number",
              "canBeUsedToMatch": true
            },
            {
              "id": "created_at",
              "displayName": "created_at",
              "required": true,
              "defaultMatch": false,
              "display": true,
              "type": "dateTime",
              "canBeUsedToMatch": true
            },
            {
              "id": "updated_at",
              "displayName": "updated_at",
              "required": true,
              "defaultMatch": false,
              "display": true,
              "type": "dateTime",
              "canBeUsedToMatch": true
            },
            {
              "id": "first_name",
              "displayName": "first_name",
              "required": false,
              "defaultMatch": false,
              "display": true,
              "type": "string",
              "canBeUsedToMatch": true
            },
            {
              "id": "last_name",
              "displayName": "last_name",
              "required": false,
              "defaultMatch": false,
              "display": true,
              "type": "string",
              "canBeUsedToMatch": true
            },
            {
              "id": "phone",
              "displayName": "phone",
              "required": false,
              "defaultMatch": false,
              "display": true,
              "type": "string",
              "canBeUsedToMatch": true
            },
            {
              "id": "email",
              "displayName": "email",
              "required": false,
              "defaultMatch": false,
              "display": true,
              "type": "string",
              "canBeUsedToMatch": true
            },
            {
              "id": "city",
              "displayName": "city",
              "required": false,
              "defaultMatch": false,
              "display": true,
              "type": "string",
              "canBeUsedToMatch": true
            },
            {
              "id": "coming_from",
              "displayName": "coming_from",
              "required": false,
              "defaultMatch": false,
              "display": true,
              "type": "string",
              "canBeUsedToMatch": true
            },
            {
              "id": "gcl_id",
              "displayName": "gcl_id",
              "required": false,
              "defaultMatch": false,
              "display": true,
              "type": "string",
              "canBeUsedToMatch": true
            },
            {
              "id": "whatsapp_opt_in",
              "displayName": "whatsapp_opt_in",
              "required": false,
              "defaultMatch": false,
              "display": true,
              "type": "boolean",
              "canBeUsedToMatch": true
            },
            {
              "id": "register_for_webinar",
              "displayName": "register_for_webinar",
              "required": false,
              "defaultMatch": false,
              "display": true,
              "type": "boolean",
              "canBeUsedToMatch": true
            },
            {
              "id": "intrested_to_work_in_us",
              "displayName": "intrested_to_work_in_us",
              "required": false,
              "defaultMatch": false,
              "display": true,
              "type": "boolean",
              "canBeUsedToMatch": true
            },
            {
              "id": "page_full_url",
              "displayName": "page_full_url",
              "required": false,
              "defaultMatch": false,
              "display": true,
              "type": "string",
              "canBeUsedToMatch": true
            },
            {
              "id": "url_page_path",
              "displayName": "url_page_path",
              "required": false,
              "defaultMatch": false,
              "display": true,
              "type": "string",
              "canBeUsedToMatch": true
            },
            {
              "id": "linkedin_url",
              "displayName": "linkedin_url",
              "required": false,
              "defaultMatch": false,
              "display": true,
              "type": "string",
              "canBeUsedToMatch": true
            },
            {
              "id": "isFromWelcomeBack",
              "displayName": "isFromWelcomeBack",
              "required": true,
              "defaultMatch": false,
              "display": true,
              "type": "boolean",
              "canBeUsedToMatch": true
            },
            {
              "id": "uuid",
              "displayName": "uuid",
              "required": false,
              "defaultMatch": false,
              "display": true,
              "type": "string",
              "canBeUsedToMatch": true
            },
            {
              "id": "program_id",
              "displayName": "program_id",
              "required": false,
              "defaultMatch": false,
              "display": true,
              "type": "number",
              "canBeUsedToMatch": true
            },
            {
              "id": "campaign_id",
              "displayName": "campaign_id",
              "required": false,
              "defaultMatch": false,
              "display": true,
              "type": "number",
              "canBeUsedToMatch": true
            },
            {
              "id": "educationQualificationId",
              "displayName": "educationQualificationId",
              "required": false,
              "defaultMatch": false,
              "display": true,
              "type": "number",
              "canBeUsedToMatch": true
            },
            {
              "id": "leadId",
              "displayName": "leadId",
              "required": false,
              "defaultMatch": false,
              "display": true,
              "type": "number",
              "canBeUsedToMatch": true
            }
          ]
        },
        "options": {}
      },
      "id": "6a46b0ce-0347-4e8a-8d93-a7857846507c",
      "name": "Postgres1",
      "type": "n8n-nodes-base.postgres",
      "typeVersion": 2.2,
      "position": [
        1700,
        520
      ],
      "credentials": {
        "postgres": {
          "id": "VPJUosohtvWNBW4H",
          "name": "MF Prod (DO NOT USE)"
        }
      }
    }
  ],
  "pinData": {},
  "settings": {
    "executionOrder": "v1"
  },
  "staticData": null,
  "tags": [],
  "triggerCount": 0,
  "updatedAt": "2025-02-05T06:20:02.000Z",
  "versionId": "2d1edf4c-f757-4a9a-8212-afd6201a5439"
}