{
  "active": true,
  "connections": {
    "IIML1": {
      "main": [
        [
          {
            "node": "Set16",
            "type": "main",
            "index": 0
          }
        ]
      ]
    },
    "FRM1": {
      "main": [
        [
          {
            "node": "Set",
            "type": "main",
            "index": 0
          }
        ]
      ]
    },
    "CFA1": {
      "main": [
        [
          {
            "node": "Set15",
            "type": "main",
            "index": 0
          }
        ]
      ]
    },
    "Set": {
      "main": [
        [
          {
            "node": "HTTP Request",
            "type": "main",
            "index": 0
          }
        ]
      ]
    },
    "Set15": {
      "main": [
        [
          {
            "node": "HTTP Request17",
            "type": "main",
            "index": 0
          }
        ]
      ]
    },
    "Set16": {
      "main": [
        [
          {
            "node": "HTTP Request18",
            "type": "main",
            "index": 0
          }
        ]
      ]
    },
    "Switch": {
      "main": [
        [
          {
            "node": "CFA1",
            "type": "main",
            "index": 0
          }
        ],
        [
          {
            "node": "FRM1",
            "type": "main",
            "index": 0
          }
        ],
        [
          {
            "node": "IIML1",
            "type": "main",
            "index": 0
          }
        ]
      ]
    },
    "IF1": {
      "main": [
        [
          {
            "node": "IF12",
            "type": "main",
            "index": 0
          }
        ],
        [
          {
            "node": "Switch",
            "type": "main",
            "index": 0
          }
        ]
      ]
    },
    "WhatsApp Business Cloud7": {
      "main": [
        [
          {
            "node": "Set17",
            "type": "main",
            "index": 0
          }
        ]
      ]
    },
    "Set17": {
      "main": [
        [
          {
            "node": "HTTP Request19",
            "type": "main",
            "index": 0
          }
        ]
      ]
    },
    "WhatsApp Business Cloud8": {
      "main": [
        [
          {
            "node": "Set18",
            "type": "main",
            "index": 0
          }
        ]
      ]
    },
    "Set18": {
      "main": [
        [
          {
            "node": "HTTP Request20",
            "type": "main",
            "index": 0
          }
        ]
      ]
    },
    "WhatsApp Business Cloud9": {
      "main": [
        [
          {
            "node": "Set19",
            "type": "main",
            "index": 0
          }
        ]
      ]
    },
    "Set19": {
      "main": [
        [
          {
            "node": "HTTP Request21",
            "type": "main",
            "index": 0
          }
        ]
      ]
    },
    "IF10": {
      "main": [
        [
          {
            "node": "WhatsApp Business Cloud7",
            "type": "main",
            "index": 0
          }
        ],
        [
          {
            "node": "WhatsApp Business Cloud8",
            "type": "main",
            "index": 0
          }
        ]
      ]
    },
    "IF11": {
      "main": [
        [
          {
            "node": "IF10",
            "type": "main",
            "index": 0
          }
        ],
        [
          {
            "node": "WhatsApp Business Cloud1",
            "type": "main",
            "index": 0
          }
        ]
      ]
    },
    "IF12": {
      "main": [
        [
          {
            "node": "IF11",
            "type": "main",
            "index": 0
          }
        ],
        [
          {
            "node": "WhatsApp Business Cloud9",
            "type": "main",
            "index": 0
          }
        ]
      ]
    },
    "WhatsApp Business Cloud1": {
      "main": [
        [
          {
            "node": "Set20",
            "type": "main",
            "index": 0
          }
        ]
      ]
    },
    "Set20": {
      "main": [
        [
          {
            "node": "HTTP Request22",
            "type": "main",
            "index": 0
          }
        ]
      ]
    },
    "Schedule Trigger1": {
      "main": [
        [
          {
            "node": "Day 2",
            "type": "main",
            "index": 0
          }
        ]
      ]
    },
    "Day 2": {
      "main": [
        [
          {
            "node": "IF1",
            "type": "main",
            "index": 0
          }
        ]
      ]
    }
  },
  "createdAt": "2024-06-05T12:37:39.311Z",
  "id": "XONaV6UC3jxIaGMT",
  "meta": null,
  "name": "reminder 2 day",
  "nodes": [
    {
      "parameters": {
        "phoneNumberId": "171009622770823",
        "recipientPhoneNumber": "={{ $json.lead_details.phone }}",
        "template": "533_booking_failed_reminder_3|en",
        "components": {
          "component": [
            {
              "bodyParameters": {
                "parameter": [
                  {
                    "text": "={{ $json.lead_details.first_name }}"
                  }
                ]
              }
            },
            {
              "type": "header",
              "headerParameters": {
                "parameter": [
                  {
                    "type": "image",
                    "imageLink": "https://blcwdqfhupddorxpdcjl.supabase.co/storage/v1/object/public/wa_assets/533_booking_failed_reminder_3.png"
                  }
                ]
              }
            }
          ]
        }
      },
      "id": "cd98f66f-b0c6-47ce-be70-a8eb2254ca7a",
      "name": "IIML1",
      "type": "n8n-nodes-base.whatsApp",
      "typeVersion": 1,
      "position": [
        -360,
        2640
      ],
      "credentials": {
        "whatsAppApi": {
          "id": "JPvNp2kC4SudtNkr",
          "name": "WhatsApp account New"
        }
      }
    },
    {
      "parameters": {
        "phoneNumberId": "171009622770823",
        "recipientPhoneNumber": "={{ $json.lead_details.phone }}",
        "template": "433_booking_failed_reminder_3|en",
        "components": {
          "component": [
            {
              "bodyParameters": {
                "parameter": [
                  {
                    "text": "={{ $json.lead_details.first_name }}"
                  }
                ]
              }
            },
            {
              "type": "header",
              "headerParameters": {
                "parameter": [
                  {
                    "type": "image",
                    "imageLink": "https://blcwdqfhupddorxpdcjl.supabase.co/storage/v1/object/public/wa_assets/433_booking_failed_reminder_3.png"
                  }
                ]
              }
            }
          ]
        }
      },
      "id": "4b6fd72c-9154-4318-b136-87b4a0285322",
      "name": "FRM1",
      "type": "n8n-nodes-base.whatsApp",
      "typeVersion": 1,
      "position": [
        -360,
        2420
      ],
      "credentials": {
        "whatsAppApi": {
          "id": "JPvNp2kC4SudtNkr",
          "name": "WhatsApp account New"
        }
      }
    },
    {
      "parameters": {
        "phoneNumberId": "171009622770823",
        "recipientPhoneNumber": "={{ $json.lead_details.phone }}",
        "template": "333_booking_failed_reminder_3 | en",
        "components": {
          "component": [
            {
              "bodyParameters": {
                "parameter": [
                  {
                    "text": "={{ $json.lead_details.first_name }}"
                  }
                ]
              }
            },
            {
              "type": "header",
              "headerParameters": {
                "parameter": [
                  {
                    "type": "image",
                    "imageLink": "https://blcwdqfhupddorxpdcjl.supabase.co/storage/v1/object/public/wa_assets/333_booking_failed_reminder_3.png"
                  }
                ]
              }
            }
          ]
        }
      },
      "id": "be4d8ba8-5ced-43ec-ba92-91f714101a1b",
      "name": "CFA1",
      "type": "n8n-nodes-base.whatsApp",
      "typeVersion": 1,
      "position": [
        -360,
        2160
      ],
      "credentials": {
        "whatsAppApi": {
          "id": "JPvNp2kC4SudtNkr",
          "name": "WhatsApp account New"
        }
      }
    },
    {
      "parameters": {
        "values": {
          "string": [
            {
              "name": "message",
              "value": "=433_booking_failed_reminder_3|en"
            }
          ]
        },
        "options": {}
      },
      "id": "67e8a932-9b66-499b-9f6b-645f873a5240",
      "name": "Set",
      "type": "n8n-nodes-base.set",
      "typeVersion": 2,
      "position": [
        -200,
        2420
      ]
    },
    {
      "parameters": {
        "method": "POST",
        "url": "https://webhook.miles-api.com/webhook/create-send-message",
        "sendBody": true,
        "specifyBody": "json",
        "jsonBody": "={\n    \"camp_id\":356,\n    \"message_id\":\"{{ $json.messages[0].id }}\",\n    \"message\":\"{{ $json.message }}\",\n    \"mobile\":{{ $json.contacts[0].wa_id }},\n    \"sender_id\":917338649613,\n\"next_flow\":\"Mfke1kvGEi1aq2E5\",\n\"lead_dump_id\":{{ $('1 Day Check | IF - office visit is completed (form - 2 is completed) then exit').item.json.lead_details.id }},\n\"template\":\"433_booking_failed_reminder_3|en\"\n}",
        "options": {}
      },
      "id": "a96029f4-9a1f-4bd7-bd42-037d60f0dc98",
      "name": "HTTP Request",
      "type": "n8n-nodes-base.httpRequest",
      "typeVersion": 4.1,
      "position": [
        -40,
        2420
      ],
      "continueOnFail": true
    },
    {
      "parameters": {
        "values": {
          "string": [
            {
              "name": "message",
              "value": "=333_booking_failed_reminder_3 | en"
            }
          ]
        },
        "options": {}
      },
      "id": "b296c603-0952-4c0c-a4d8-00c8c3ffd40c",
      "name": "Set15",
      "type": "n8n-nodes-base.set",
      "typeVersion": 2,
      "position": [
        -200,
        2160
      ]
    },
    {
      "parameters": {
        "method": "POST",
        "url": "https://webhook.miles-api.com/webhook/create-send-message",
        "sendBody": true,
        "specifyBody": "json",
        "jsonBody": "={\n    \"camp_id\":356,\n    \"message_id\":\"{{ $json.messages[0].id }}\",\n    \"message\":\"{{ $json.message }}\",\n    \"mobile\":{{ $json.contacts[0].wa_id }},\n    \"sender_id\":917338649613,\n\"next_flow\":\"Mfke1kvGEi1aq2E5\",\n\"lead_dump_id\":{{ $('1 Day Check | IF - office visit is completed (form - 2 is completed) then exit').item.json.lead_details.id }},\n\"template\":\"333_booking_failed_reminder_3 | en\"\n}",
        "options": {}
      },
      "id": "53da292d-3d1d-4ca5-afc2-1313401bb66f",
      "name": "HTTP Request17",
      "type": "n8n-nodes-base.httpRequest",
      "typeVersion": 4.1,
      "position": [
        -40,
        2160
      ],
      "continueOnFail": true
    },
    {
      "parameters": {
        "values": {
          "string": [
            {
              "name": "message",
              "value": "=533_booking_failed_reminder_3|en"
            }
          ]
        },
        "options": {}
      },
      "id": "c5be7b7e-ce17-4702-9fea-37d166788309",
      "name": "Set16",
      "type": "n8n-nodes-base.set",
      "typeVersion": 2,
      "position": [
        -200,
        2640
      ]
    },
    {
      "parameters": {
        "method": "POST",
        "url": "https://webhook.miles-api.com/webhook/create-send-message",
        "sendBody": true,
        "specifyBody": "json",
        "jsonBody": "={\n    \"camp_id\":356,\n    \"message_id\":\"{{ $json.messages[0].id }}\",\n    \"message\":\"{{ $json.message }}\",\n    \"mobile\":{{ $json.contacts[0].wa_id }},\n    \"sender_id\":917338649613,\n\"next_flow\":\"Mfke1kvGEi1aq2E5\",\n\"lead_dump_id\":{{ $('1 Day Check | IF - office visit is completed (form - 2 is completed) then exit').item.json.lead_details.id }},\n\"template\":\"533_booking_failed_reminder_3|en\"\n}",
        "options": {}
      },
      "id": "00c991ed-6edb-4b40-9a5d-9c6c850c4e28",
      "name": "HTTP Request18",
      "type": "n8n-nodes-base.httpRequest",
      "typeVersion": 4.1,
      "position": [
        -40,
        2640
      ],
      "continueOnFail": true
    },
    {
      "parameters": {
        "mode": "expression",
        "output": "={{ $json.course == 4 ? 0 : $json.course == 5 ? 1 :2 }}"
      },
      "id": "78571569-fa1c-4b3d-9624-ac3919eb5340",
      "name": "Switch",
      "type": "n8n-nodes-base.switch",
      "typeVersion": 1,
      "position": [
        -580,
        2500
      ]
    },
    {
      "parameters": {
        "conditions": {
          "boolean": [
            {
              "value1": "={{ $json.course == 4 || $json.course == 5 || $json.course == 6 }}"
            }
          ]
        }
      },
      "id": "a7110e99-a96d-4279-8573-0bcf8ffa83e4",
      "name": "IF1",
      "type": "n8n-nodes-base.if",
      "typeVersion": 1,
      "position": [
        -800,
        1920
      ]
    },
    {
      "parameters": {
        "phoneNumberId": "171009622770823",
        "recipientPhoneNumber": "={{ $json.lead_details.phone }}",
        "template": "133_booking_failed_reminder_3|en",
        "components": {
          "component": [
            {
              "bodyParameters": {
                "parameter": [
                  {
                    "text": "={{ $json.lead_details.first_name }}"
                  }
                ]
              }
            },
            {
              "type": "header",
              "headerParameters": {
                "parameter": [
                  {
                    "type": "image",
                    "imageLink": "https://blcwdqfhupddorxpdcjl.supabase.co/storage/v1/object/public/wa_assets/133_booking_failed_reminder_3.jpg"
                  }
                ]
              }
            }
          ]
        }
      },
      "id": "26838682-98ec-4f40-a709-06227f888471",
      "name": "WhatsApp Business Cloud7",
      "type": "n8n-nodes-base.whatsApp",
      "typeVersion": 1,
      "position": [
        -40,
        1160
      ],
      "credentials": {
        "whatsAppApi": {
          "id": "JPvNp2kC4SudtNkr",
          "name": "WhatsApp account New"
        }
      }
    },
    {
      "parameters": {
        "values": {
          "string": [
            {
              "name": "message",
              "value": "=133_booking_failed_reminder_3|en"
            }
          ]
        },
        "options": {}
      },
      "id": "6fba3bb4-b9ca-46e7-8ec3-c783c2cfdd05",
      "name": "Set17",
      "type": "n8n-nodes-base.set",
      "typeVersion": 2,
      "position": [
        140,
        1160
      ]
    },
    {
      "parameters": {
        "method": "POST",
        "url": "https://webhook.miles-api.com/webhook/create-send-message",
        "sendBody": true,
        "specifyBody": "json",
        "jsonBody": "={\n    \"camp_id\":356,\n    \"message_id\":\"{{ $json.messages[0].id }}\",\n    \"message\":\"{{ $json.message }}\",\n    \"mobile\":{{ $json.contacts[0].wa_id }},\n    \"sender_id\":917338649613,\n\"next_flow\":\"Mfke1kvGEi1aq2E5\",\n\"lead_dump_id\":{{ $('1 Day Check | IF - office visit is completed (form - 2 is completed) then exit').item.json.lead_details.id }},\n\"template\":\"133_booking_failed_reminder_3|en\"\n}",
        "options": {}
      },
      "id": "9a86cfea-d220-4223-9d39-0be82ffc5011",
      "name": "HTTP Request19",
      "type": "n8n-nodes-base.httpRequest",
      "typeVersion": 4.1,
      "position": [
        320,
        1160
      ],
      "continueOnFail": true
    },
    {
      "parameters": {
        "phoneNumberId": "171009622770823",
        "recipientPhoneNumber": "={{ $json.lead_details.phone }}",
        "template": "233_booking_failed_reminder_3|en",
        "components": {
          "component": [
            {
              "bodyParameters": {
                "parameter": [
                  {
                    "text": "={{ $json.lead_details.first_name }}"
                  }
                ]
              }
            },
            {
              "type": "header",
              "headerParameters": {
                "parameter": [
                  {
                    "type": "image",
                    "imageLink": "https://blcwdqfhupddorxpdcjl.supabase.co/storage/v1/object/public/wa_assets/233_booking_failed_reminder_3.png"
                  }
                ]
              }
            }
          ]
        }
      },
      "id": "7748c30a-4fd6-4e8a-95c1-68c39dcf440b",
      "name": "WhatsApp Business Cloud8",
      "type": "n8n-nodes-base.whatsApp",
      "typeVersion": 1,
      "position": [
        -40,
        1400
      ],
      "credentials": {
        "whatsAppApi": {
          "id": "JPvNp2kC4SudtNkr",
          "name": "WhatsApp account New"
        }
      }
    },
    {
      "parameters": {
        "values": {
          "string": [
            {
              "name": "message",
              "value": "=233_booking_failed_reminder_3|en"
            }
          ]
        },
        "options": {}
      },
      "id": "e6c2209d-1311-4ec6-946c-c17016d7c5d5",
      "name": "Set18",
      "type": "n8n-nodes-base.set",
      "typeVersion": 2,
      "position": [
        120,
        1400
      ]
    },
    {
      "parameters": {
        "method": "POST",
        "url": "https://webhook.miles-api.com/webhook/create-send-message",
        "sendBody": true,
        "specifyBody": "json",
        "jsonBody": "={\n    \"camp_id\":356,\n    \"message_id\":\"{{ $json.messages[0].id }}\",\n    \"message\":\"{{ $json.message }}\",\n    \"mobile\":{{ $json.contacts[0].wa_id }},\n    \"sender_id\":917338649613,\n\"next_flow\":\"Mfke1kvGEi1aq2E5\",\n\"lead_dump_id\":{{ $('1 Day Check | IF - office visit is completed (form - 2 is completed) then exit').item.json.lead_details.id }},\n\"template\":\"233_booking_failed_reminder_3|en\"\n}",
        "options": {}
      },
      "id": "49536670-077f-4907-a6f0-75121058ed94",
      "name": "HTTP Request20",
      "type": "n8n-nodes-base.httpRequest",
      "typeVersion": 4.1,
      "position": [
        280,
        1400
      ],
      "continueOnFail": true
    },
    {
      "parameters": {
        "phoneNumberId": "=171009622770823",
        "recipientPhoneNumber": "{{ $json.lead_details.phone }}",
        "template": "233_booking_failed_reminder_3|en",
        "components": {
          "component": [
            {
              "bodyParameters": {
                "parameter": [
                  {
                    "text": "{{ $json.lead_details.first_name }}"
                  }
                ]
              }
            },
            {
              "type": "header",
              "headerParameters": {
                "parameter": [
                  {
                    "type": "image",
                    "imageLink": "=https://blcwdqfhupddorxpdcjl.supabase.co/storage/v1/object/public/wa_assets/233_booking_failed_reminder_3.png"
                  }
                ]
              }
            }
          ]
        }
      },
      "id": "a71c6424-517a-436b-90e4-8214b6694e10",
      "name": "WhatsApp Business Cloud9",
      "type": "n8n-nodes-base.whatsApp",
      "typeVersion": 1,
      "position": [
        -40,
        1800
      ],
      "credentials": {
        "whatsAppApi": {
          "id": "JPvNp2kC4SudtNkr",
          "name": "WhatsApp account New"
        }
      }
    },
    {
      "parameters": {
        "values": {
          "string": [
            {
              "name": "message",
              "value": "=233_booking_failed_reminder_3|en"
            }
          ]
        },
        "options": {}
      },
      "id": "7991821d-bd9a-49f4-b802-d0c68ed7bd4c",
      "name": "Set19",
      "type": "n8n-nodes-base.set",
      "typeVersion": 2,
      "position": [
        140,
        1800
      ]
    },
    {
      "parameters": {
        "method": "POST",
        "url": "https://webhook.miles-api.com/webhook/create-send-message",
        "sendBody": true,
        "specifyBody": "json",
        "jsonBody": "={\n    \"camp_id\":356,\n    \"message_id\":\"{{ $json.messages[0].id }}\",\n    \"message\":\"{{ $json.message }}\",\n    \"mobile\":{{ $json.contacts[0].wa_id }},\n    \"sender_id\":917338649613,\n\"next_flow\":\"Mfke1kvGEi1aq2E5\",\n\"lead_dump_id\":{{ $('1 Day Check | IF - office visit is completed (form - 2 is completed) then exit').item.json.lead_details.id }},\n\"template\":\"233_booking_failed_reminder_3|en\"\n}",
        "options": {}
      },
      "id": "ae965eba-252c-438c-a429-362e27243abf",
      "name": "HTTP Request21",
      "type": "n8n-nodes-base.httpRequest",
      "typeVersion": 4.1,
      "position": [
        320,
        1800
      ],
      "continueOnFail": true
    },
    {
      "parameters": {
        "conditions": {
          "number": [
            {
              "value1": "={{ $json.course }}",
              "operation": "equal",
              "value2": 2
            }
          ]
        }
      },
      "id": "13cc3be5-b42a-443c-bd1e-8ad96a09ade1",
      "name": "IF10",
      "type": "n8n-nodes-base.if",
      "typeVersion": 1,
      "position": [
        -320,
        1260
      ]
    },
    {
      "parameters": {
        "conditions": {
          "string": [
            {
              "value1": "={{ $json.intrested_in }}",
              "value2": "No"
            }
          ]
        }
      },
      "id": "4e2583d9-2b9a-45cb-8a01-3270fb10fa4b",
      "name": "IF11",
      "type": "n8n-nodes-base.if",
      "typeVersion": 1,
      "position": [
        -480,
        1440
      ]
    },
    {
      "parameters": {
        "conditions": {
          "string": [
            {
              "value1": "={{ $json.education_qualification }}",
              "operation": "notContains",
              "value2": "will_graduate_in_2025_or_later"
            }
          ]
        }
      },
      "id": "e063f2ee-cea5-4df3-a1f0-549a881d7cf7",
      "name": "IF12",
      "type": "n8n-nodes-base.if",
      "typeVersion": 1,
      "position": [
        -620,
        1660
      ]
    },
    {
      "parameters": {
        "phoneNumberId": "=171009622770823",
        "recipientPhoneNumber": "={{ $json.phone }}",
        "template": "733_booking_failed_reminder_3|en",
        "components": {
          "component": [
            {
              "bodyParameters": {
                "parameter": [
                  {
                    "text": "={{ $json.first_name }}"
                  }
                ]
              }
            },
            {
              "type": "header",
              "headerParameters": {
                "parameter": [
                  {
                    "type": "image",
                    "imageLink": "=https://one.mileseducation.us/storage/v1/object/public/wa_assets/m102_usp.jpg"
                  }
                ]
              }
            }
          ]
        }
      },
      "id": "2db76b16-d551-423d-983c-31ffa987b87a",
      "name": "WhatsApp Business Cloud1",
      "type": "n8n-nodes-base.whatsApp",
      "typeVersion": 1,
      "position": [
        -40,
        1580
      ],
      "credentials": {
        "whatsAppApi": {
          "id": "JPvNp2kC4SudtNkr",
          "name": "WhatsApp account New"
        }
      }
    },
    {
      "parameters": {
        "values": {
          "string": [
            {
              "name": "message",
              "value": "=733_booking_failed_reminder_3 |en"
            }
          ]
        },
        "options": {}
      },
      "id": "7c658dac-980e-4261-96db-a01e16a5ee85",
      "name": "Set20",
      "type": "n8n-nodes-base.set",
      "typeVersion": 2,
      "position": [
        120,
        1580
      ]
    },
    {
      "parameters": {
        "method": "POST",
        "url": "https://webhook.miles-api.com/webhook/create-send-message",
        "sendBody": true,
        "specifyBody": "json",
        "jsonBody": "={\n    \"camp_id\":356,\n    \"message_id\":\"{{ $json.messages[0].id }}\",\n    \"message\":\"{{ $json.message }}\",\n    \"mobile\":{{ $json.contacts[0].wa_id }},\n    \"sender_id\":917338649613,\n\"next_flow\":\"Mfke1kvGEi1aq2E5\",\n\"lead_dump_id\":{{ $('IF11').item.json.id }},\n\"template\":\"733_booking_failed_reminder_3 |en\"\n}",
        "options": {}
      },
      "id": "17c032da-e4cb-4bab-9971-3e0643c133a2",
      "name": "HTTP Request22",
      "type": "n8n-nodes-base.httpRequest",
      "typeVersion": 4.1,
      "position": [
        280,
        1580
      ],
      "continueOnFail": true
    },
    {
      "parameters": {
        "rule": {
          "interval": [
            {
              "field": "cronExpression",
              "expression": "30 8 * * *"
            }
          ]
        }
      },
      "id": "44b18d37-1b90-481f-bcd6-3a3e5245d463",
      "name": "Schedule Trigger1",
      "type": "n8n-nodes-base.scheduleTrigger",
      "typeVersion": 1.1,
      "position": [
        -1460,
        1920
      ]
    },
    {
      "parameters": {
        "method": "POST",
        "url": "https://blcwdqfhupddorxpdcjl.supabase.co/rest/v1/rpc/get_form_fill_remainder_with_id",
        "sendHeaders": true,
        "headerParameters": {
          "parameters": [
            {
              "name": "ApiKey",
              "value": " eyJhbGciOiJIUzI1NiIsInR5cCI6IkpXVCJ9.eyJpc3MiOiJzdXBhYmFzZSIsInJlZiI6ImJsY3dkcWZodXBkZG9yeHBkY2psIiwicm9sZSI6ImFub24iLCJpYXQiOjE2OTI4NzkxMjgsImV4cCI6MjAwODQ1NTEyOH0.NdAhT3uGNwQahfxxUKM8BGV-gEjuIpl8NKVPpcaSFGM"
            }
          ]
        },
        "sendBody": true,
        "bodyParameters": {
          "parameters": [
            {
              "name": "interval_number",
              "value": "2"
            }
          ]
        },
        "options": {}
      },
      "id": "1f1fbbd5-7ad4-42cd-8a56-2d20ea781b21",
      "name": "Day 2",
      "type": "n8n-nodes-base.httpRequest",
      "typeVersion": 4.1,
      "position": [
        -1120,
        1920
      ]
    }
  ],
  "pinData": {},
  "settings": {
    "executionOrder": "v1",
    "timezone": "Asia/Calcutta",
    "saveManualExecutions": true,
    "callerPolicy": "workflowsFromSameOwner"
  },
  "staticData": {
    "node:Schedule Trigger1": {
      "recurrencyRules": []
    }
  },
  "tags": [],
  "triggerCount": 1,
  "updatedAt": "2024-07-10T07:28:39.000Z",
  "versionId": "197c05df-6d11-4f77-8c1a-abc26ad1b711"
}